AskCodeium/__init__.py
AskCodeium/services/__init__.py
AskCodeium/services/create_chat.py
AskCodeium/utils/__init__.py
AskCodeium/utils/browser_manager.py
AskCodeium-1.0.6.dist-info/METADATA
AskCodeium-1.0.6.dist-info/WHEEL
AskCodeium-1.0.6.dist-info/top_level.txt
AskCodeium-1.0.6.dist-info/RECORD
