Metadata-Version: 2.1
Name: AskCodeium
Version: 1.0.6
Requires-Dist: selenium >=4.6.0
